{"dependencies":[{"name":"_css_loader"}],"generated":{"css":"@keyframes lamp\n{\n0% {\n  transform: rotate(7deg);\n  transform-origin: 50% 0\n}\n50% {\n  transform: rotate(-7deg);\n  transform-origin: 50% 0\n}\n100% {\n  transform: rotate(7deg);\n  transform-origin: 50% 0\n}\n}\n@keyframes xian\n{\n0% {\n  top: -5vh;\n}\n50% {\n  top: -2vh;\n}\n100% {\n  top: -5vh;\n}\n}\n\n\n.lampwarp{\n  width: 100vw;\n  height: 100vh;\n  position: absolute;\n  top: 0;\n  left: 0;\n  overflow: hidden;\n}\n\n\n.lamp{\n  animation: lamp 2s infinite;\n}\n.xian{\n  position: absolute;\n  top: -80vw;\n  right: 10vw;\n  z-index: 100;\n  width: 8vw;\n  animation: xian 4s infinite;\n}\n","js":"\n        var reloadCSS = require('_css_loader');\n        module.hot.dispose(reloadCSS);\n        module.hot.accept(reloadCSS);\n      "},"hash":"8020f6b606947fbc40ac3da3d45d9c6d","cacheData":{}}