{"dependencies":[{"name":"/Users/NoBey/mybs/.babelrc","includedInParent":true,"mtime":1526114216000},{"name":"/Users/NoBey/mybs/package.json","includedInParent":true,"mtime":1526668717000},{"name":"react","loc":{"line":1,"column":21}},{"name":"react-dom","loc":{"line":2,"column":21}},{"name":"./lamp.css","loc":{"line":3,"column":7}},{"name":"./img/lamp/8.png","loc":{"line":4,"column":17}},{"name":"./img/lamp/2.png","loc":{"line":5,"column":18}},{"name":"./img/lamp/4.png","loc":{"line":6,"column":17}}],"generated":{"js":"\"use strict\";Object.defineProperty(exports,\"__esModule\",{value:!0});var e=Object.assign||function(e){for(var t=1;t<arguments.length;t++){var r=arguments[t];for(var n in r)Object.prototype.hasOwnProperty.call(r,n)&&(e[n]=r[n])}return e},t=function(){function e(e,t){for(var r=0;r<t.length;r++){var n=t[r];n.enumerable=n.enumerable||!1,n.configurable=!0,\"value\"in n&&(n.writable=!0),Object.defineProperty(e,n.key,n)}}return function(t,r,n){return r&&e(t.prototype,r),n&&e(t,n),t}}(),r=require(\"react\"),n=p(r),o=require(\"react-dom\"),a=p(o);require(\"./lamp.css\");var i=require(\"./img/lamp/8.png\"),u=p(i),l=require(\"./img/lamp/2.png\"),c=p(l),s=require(\"./img/lamp/4.png\"),f=p(s);function p(e){return e&&e.__esModule?e:{default:e}}function m(e,t){if(!(e instanceof t))throw new TypeError(\"Cannot call a class as a function\")}function d(e,t){if(!e)throw new ReferenceError(\"this hasn't been initialised - super() hasn't been called\");return!t||\"object\"!=typeof t&&\"function\"!=typeof t?e:t}function y(e,t){if(\"function\"!=typeof t&&null!==t)throw new TypeError(\"Super expression must either be null or a function, not \"+typeof t);e.prototype=Object.create(t&&t.prototype,{constructor:{value:e,enumerable:!1,writable:!0,configurable:!0}}),t&&(Object.setPrototypeOf?Object.setPrototypeOf(e,t):e.__proto__=t)}var b=function(r){function o(e){m(this,o);var t=d(this,(o.__proto__||Object.getPrototypeOf(o)).call(this,e));return t.state={ok:!1},t}return y(o,n.default.Component),t(o,[{key:\"componentDidMount\",value:function(){}},{key:\"render\",value:function(){var t=this,r=this.state.ok;return n.default.createElement(\"div\",e({className:\"lampwarp\"},this.props),r?n.default.createElement(\"img\",{className:\"lamp \",style:{width:\"100vw\"},src:u.default}):n.default.createElement(\"img\",{className:\"lamp \",style:{width:\"24vw\",position:\"absolute\",marginLeft:\"38vw\"},src:c.default}),n.default.createElement(\"img\",{className:\"down xian\",src:f.default,onClick:function(){return t.setState({ok:!r})}}))}}]),o}();exports.default=b;","map":{"mappings":[{"generated":{"line":11,"column":0},"source":"lamp.js","original":{"line":1,"column":0}},{"generated":{"line":15,"column":0},"source":"lamp.js","original":{"line":2,"column":0}},{"generated":{"line":19,"column":0},"source":"lamp.js","original":{"line":3,"column":0}},{"generated":{"line":21,"column":0},"source":"lamp.js","original":{"line":4,"column":0}},{"generated":{"line":25,"column":0},"source":"lamp.js","original":{"line":5,"column":0}},{"generated":{"line":29,"column":0},"source":"lamp.js","original":{"line":6,"column":0}},{"name":"Lamp","generated":{"line":41,"column":4},"source":"lamp.js","original":{"line":8,"column":22}},{"generated":{"line":44,"column":0},"source":"lamp.js","original":{"line":9,"column":2}},{"name":"props","generated":{"line":44,"column":16},"source":"lamp.js","original":{"line":9,"column":14}},{"generated":{"line":44,"column":21},"source":"lamp.js","original":{"line":9,"column":2}},{"generated":{"line":44,"column":23},"source":"lamp.js","original":{"line":9,"column":21}},{"generated":{"line":45,"column":0},"source":"lamp.js","original":{"line":9,"column":21}},{"generated":{"line":47,"column":0},"source":"lamp.js","original":{"line":9,"column":21}},{"name":"props","generated":{"line":47,"column":108},"source":"lamp.js","original":{"line":10,"column":12}},{"generated":{"line":47,"column":113},"source":"lamp.js","original":{"line":9,"column":21}},{"generated":{"line":49,"column":0},"source":"lamp.js","original":{"line":11,"column":6}},{"name":"state","generated":{"line":49,"column":10},"source":"lamp.js","original":{"line":11,"column":11}},{"generated":{"line":49,"column":15},"source":"lamp.js","original":{"line":11,"column":6}},{"generated":{"line":49,"column":18},"source":"lamp.js","original":{"line":11,"column":19}},{"name":"ok","generated":{"line":50,"column":0},"source":"lamp.js","original":{"line":12,"column":8}},{"generated":{"line":50,"column":10},"source":"lamp.js","original":{"line":12,"column":12}},{"generated":{"line":51,"column":0},"source":"lamp.js","original":{"line":11,"column":19}},{"generated":{"line":51,"column":5},"source":"lamp.js","original":{"line":11,"column":6}},{"generated":{"line":52,"column":0},"source":"lamp.js","original":{"line":9,"column":21}},{"generated":{"line":53,"column":0},"source":"lamp.js","original":{"line":14,"column":3}},{"generated":{"line":57,"column":40},"source":"lamp.js","original":{"line":15,"column":22}},{"generated":{"line":57,"column":41},"source":"lamp.js","original":{"line":17,"column":3}},{"generated":{"line":60,"column":29},"source":"lamp.js","original":{"line":19,"column":11}},{"generated":{"line":61,"column":0},"source":"lamp.js","original":{"line":19,"column":11}},{"generated":{"line":63,"column":0},"source":"lamp.js","original":{"line":20,"column":4}},{"name":"ok","generated":{"line":63,"column":10},"source":"lamp.js","original":{"line":20,"column":10}},{"generated":{"line":63,"column":15},"source":"lamp.js","original":{"line":20,"column":15}},{"name":"state","generated":{"line":63,"column":20},"source":"lamp.js","original":{"line":20,"column":20}},{"generated":{"line":63,"column":25},"source":"lamp.js","original":{"line":20,"column":15}},{"name":"ok","generated":{"line":63,"column":26},"source":"lamp.js","original":{"line":20,"column":26}},{"generated":{"line":63,"column":28},"source":"lamp.js","original":{"line":20,"column":4}},{"generated":{"line":64,"column":0},"source":"lamp.js","original":{"line":21,"column":4}},{"generated":{"line":64,"column":13},"source":"lamp.js","original":{"line":22,"column":6}},{"generated":{"line":65,"column":0},"source":"lamp.js","original":{"line":22,"column":6}},{"generated":{"line":66,"column":0},"source":"lamp.js","original":{"line":22,"column":6}},{"generated":{"line":66,"column":19},"source":"lamp.js","original":{"line":22,"column":11}},{"generated":{"line":66,"column":30},"source":"lamp.js","original":{"line":22,"column":22}},{"generated":{"line":66,"column":40},"source":"lamp.js","original":{"line":22,"column":6}},{"generated":{"line":66,"column":44},"source":"lamp.js","original":{"line":22,"column":38}},{"name":"props","generated":{"line":66,"column":49},"source":"lamp.js","original":{"line":22,"column":43}},{"generated":{"line":66,"column":54},"source":"lamp.js","original":{"line":22,"column":6}},{"name":"ok","generated":{"line":67,"column":0},"source":"lamp.js","original":{"line":24,"column":8}},{"generated":{"line":67,"column":13},"source":"lamp.js","original":{"line":24,"column":13}},{"generated":{"line":67,"column":52},"source":"lamp.js","original":{"line":24,"column":18}},{"generated":{"line":67,"column":63},"source":"lamp.js","original":{"line":24,"column":29}},{"generated":{"line":67,"column":70},"source":"lamp.js","original":{"line":24,"column":13}},{"generated":{"line":67,"column":72},"source":"lamp.js","original":{"line":24,"column":38}},{"generated":{"line":67,"column":79},"source":"lamp.js","original":{"line":24,"column":45}},{"name":"width","generated":{"line":67,"column":81},"source":"lamp.js","original":{"line":24,"column":46}},{"generated":{"line":67,"column":88},"source":"lamp.js","original":{"line":24,"column":53}},{"generated":{"line":67,"column":95},"source":"lamp.js","original":{"line":24,"column":45}},{"generated":{"line":67,"column":97},"source":"lamp.js","original":{"line":24,"column":13}},{"generated":{"line":67,"column":99},"source":"lamp.js","original":{"line":24,"column":63}},{"name":"lamp","generated":{"line":67,"column":104},"source":"lamp.js","original":{"line":24,"column":68}},{"generated":{"line":67,"column":114},"source":"lamp.js","original":{"line":24,"column":13}},{"generated":{"line":67,"column":117},"source":"lamp.js","original":{"line":24,"column":8}},{"generated":{"line":67,"column":120},"source":"lamp.js","original":{"line":24,"column":79}},{"generated":{"line":67,"column":159},"source":"lamp.js","original":{"line":24,"column":84}},{"generated":{"line":67,"column":170},"source":"lamp.js","original":{"line":24,"column":95}},{"generated":{"line":67,"column":177},"source":"lamp.js","original":{"line":24,"column":79}},{"generated":{"line":67,"column":179},"source":"lamp.js","original":{"line":24,"column":104}},{"generated":{"line":67,"column":186},"source":"lamp.js","original":{"line":24,"column":111}},{"name":"width","generated":{"line":67,"column":188},"source":"lamp.js","original":{"line":24,"column":112}},{"generated":{"line":67,"column":195},"source":"lamp.js","original":{"line":24,"column":119}},{"generated":{"line":67,"column":201},"source":"lamp.js","original":{"line":24,"column":111}},{"name":"position","generated":{"line":67,"column":203},"source":"lamp.js","original":{"line":24,"column":126}},{"generated":{"line":67,"column":213},"source":"lamp.js","original":{"line":24,"column":135}},{"generated":{"line":67,"column":223},"source":"lamp.js","original":{"line":24,"column":111}},{"name":"marginLeft","generated":{"line":67,"column":225},"source":"lamp.js","original":{"line":24,"column":146}},{"generated":{"line":67,"column":237},"source":"lamp.js","original":{"line":24,"column":158}},{"generated":{"line":67,"column":243},"source":"lamp.js","original":{"line":24,"column":111}},{"generated":{"line":67,"column":245},"source":"lamp.js","original":{"line":24,"column":79}},{"generated":{"line":67,"column":247},"source":"lamp.js","original":{"line":24,"column":167}},{"name":"lamp2","generated":{"line":67,"column":252},"source":"lamp.js","original":{"line":24,"column":172}},{"generated":{"line":67,"column":262},"source":"lamp.js","original":{"line":24,"column":79}},{"generated":{"line":67,"column":265},"source":"lamp.js","original":{"line":22,"column":6}},{"generated":{"line":68,"column":0},"source":"lamp.js","original":{"line":26,"column":6}},{"generated":{"line":68,"column":47},"source":"lamp.js","original":{"line":26,"column":11}},{"generated":{"line":68,"column":58},"source":"lamp.js","original":{"line":26,"column":22}},{"generated":{"line":68,"column":69},"source":"lamp.js","original":{"line":26,"column":6}},{"generated":{"line":68,"column":71},"source":"lamp.js","original":{"line":26,"column":35}},{"name":"xian","generated":{"line":68,"column":76},"source":"lamp.js","original":{"line":26,"column":40}},{"generated":{"line":68,"column":86},"source":"lamp.js","original":{"line":26,"column":6}},{"generated":{"line":68,"column":88},"source":"lamp.js","original":{"line":26,"column":46}},{"generated":{"line":68,"column":97},"source":"lamp.js","original":{"line":26,"column":55}},{"generated":{"line":69,"column":0},"source":"lamp.js","original":{"line":26,"column":55}},{"generated":{"line":69,"column":19},"source":"lamp.js","original":{"line":26,"column":61}},{"name":"setState","generated":{"line":69,"column":26},"source":"lamp.js","original":{"line":26,"column":66}},{"generated":{"line":69,"column":34},"source":"lamp.js","original":{"line":26,"column":61}},{"generated":{"line":69,"column":35},"source":"lamp.js","original":{"line":26,"column":75}},{"name":"ok","generated":{"line":69,"column":37},"source":"lamp.js","original":{"line":26,"column":76}},{"generated":{"line":69,"column":41},"source":"lamp.js","original":{"line":26,"column":80}},{"name":"ok","generated":{"line":69,"column":42},"source":"lamp.js","original":{"line":26,"column":81}},{"generated":{"line":69,"column":44},"source":"lamp.js","original":{"line":26,"column":75}},{"generated":{"line":69,"column":46},"source":"lamp.js","original":{"line":26,"column":61}},{"generated":{"line":69,"column":47},"source":"lamp.js","original":{"line":26,"column":55}},{"generated":{"line":70,"column":0},"source":"lamp.js","original":{"line":26,"column":55}},{"generated":{"line":70,"column":11},"source":"lamp.js","original":{"line":26,"column":6}},{"generated":{"line":71,"column":0},"source":"lamp.js","original":{"line":22,"column":6}},{"generated":{"line":71,"column":7},"source":"lamp.js","original":{"line":21,"column":4}},{"generated":{"line":72,"column":0},"source":"lamp.js","original":{"line":30,"column":3}},{"name":"React","generated":{"line":76,"column":2},"source":"lamp.js","original":{"line":8,"column":35}},{"name":"Component","generated":{"line":76,"column":18},"source":"lamp.js","original":{"line":8,"column":41}},{"name":"Lamp","generated":{"line":78,"column":18},"source":"lamp.js","original":{"line":8,"column":22}}],"sources":{"lamp.js":"import React    from 'react';\nimport ReactDOM from 'react-dom';\nimport './lamp.css'\nimport lamp from './img/lamp/8.png'\nimport lamp2 from './img/lamp/2.png'\nimport xian from './img/lamp/4.png'\n\nexport default  class Lamp extends React.Component {\n  constructor(props) {\n      super(props);\n      this.state = {\n        ok: false\n      };\n  }\n  componentDidMount() {\n\n  }\n\n  render() {\n    const ok = this.state.ok\n    return (\n      <div className={'lampwarp'} {...this.props}>\n      {\n        ok ? <img className={'lamp '} style={{width: '100vw'}} src={lamp} /> : <img className={'lamp '} style={{width: '24vw',position:'absolute',marginLeft: '38vw'}} src={lamp2} />\n      }\n      <img className={'down xian'} src={xian} onClick={() => this.setState({ok: !ok}) } />\n\n      </div>\n    );\n  }\n}\n"},"lineCount":null}},"hash":"06c15621392294ef856e2eb4ed034219","cacheData":{"env":{}}}